__init__.py
d365_relations_cli/__init__.py
d365_relations_cli/cli.py
d365_relations_cli/optimize_json.py
d365_relations_cli/table_relationships.py
d365_relations_cli/tablefieldassociations_opt.json
d365_relations_cli-0.1.4.dist-info/licenses/LICENSE
d365_relations_cli-0.1.4.dist-info/METADATA
d365_relations_cli-0.1.4.dist-info/WHEEL
d365_relations_cli-0.1.4.dist-info/entry_points.txt
d365_relations_cli-0.1.4.dist-info/top_level.txt
d365_relations_cli-0.1.4.dist-info/RECORD
