Metadata-Version: 2.4
Name: d365-relations-cli
Version: 0.1.4
Summary: Get and explore relationships between Dynamics 365 tables
Author: duggurd
Project-URL: Repository, https://github.com/duggurd/d365_tablerelations_cli
Project-URL: Documentation, https://github.com/duggurd/d365_tablerelations_cli/blob/master/README.md
Keywords: dynamics 365,relations,relationships,axapta,d365,data,cli
Requires-Python: >=3.10
License-File: LICENSE
Dynamic: license-file
